Day 15/Synchronous counter/ring counter/ring.v
module ring (input clk,rst,output reg[3:0]q);
always@(posedge clk or posedge rst)begin
if(rst)begin
q<=4'b0001;
end
else begin
q<={q[2:0],q[3]};
end
end
endmodule

Day 15/Synchronous counter/ring counter/ring_tb.v
module ring_tb;
reg clk,rst;
wire [3:0]q;
ring uut(.clk(clk),.rst(rst),.q(q));
initial begin
$dumpfile("ring.vcd");
$dumpvars();
$monitor("clk=%b,rst=%b,q=%b",clk,rst,q);
clk = 0;
rst = 1;
#10 rst = 0;
#100 $finish;
end
always #5 clk = ~clk;
endmodule

Day 15/ring counter/ring.vcd
$date
	Sat May 31 15:41:40 2025
$end
$version
	Icarus Verilog
$end
$timescale
	1s
$end
$scope module ring_tb $end
$var wire 4 ! q [3:0] $end
$var reg 1 " clk $end
$var reg 1 # rst $end
$scope module uut $end
$var wire 1 " clk $end
$var wire 1 # rst $end
$var reg 4 $ q [3:0] $end
$upscope $end
$upscope $end
$enddefinitions $end
$comment Show the parameter values. $end
$dumpall
$end
#0
$dumpvars
b1 $
1#
0"
b1 !
$end
#5
1"
#10
0"
0#
#15
b10 !
b10 $
1"
#20
0"
#25
b100 !
b100 $
1"
#30
0"
#35
b1000 !
b1000 $
1"
#40
0"
#45
b1 !
b1 $
1"
#50
0"
#55
b10 !
b10 $
1"
#60
0"
#65
b100 !
b100 $
1"
#70
0"
#75
b1000 !
b1000 $
1"
#80
0"
#85
b1 !
b1 $
1"
#90
0"
#95
b10 !
b10 $
1"
#100
0"
#105
b100 !
b100 $
1"
